aiida_sssp/__init__.py
aiida_sssp/cli/__init__.py
aiida_sssp/cli/install.py
aiida_sssp/cli/list.py
aiida_sssp/cli/options.py
aiida_sssp/cli/root.py
aiida_sssp/cli/show.py
aiida_sssp/cli/utils.py
aiida_sssp/data/__init__.py
aiida_sssp/data/parameters.py
aiida_sssp/groups/__init__.py
aiida_sssp/groups/family.py
tests/__init__.py
tests/conftest.py
tests/cli/__init__.py
tests/cli/test_install.py
tests/cli/test_list.py
tests/cli/test_root.py
tests/cli/test_show.py
tests/cli/test_utils.py
tests/data/__init__.py
tests/data/test_parameters.py
tests/groups/__init__.py
tests/groups/test_family.py
utils/__init__.py
utils/fastentrypoints.py
aiida_sssp-0.1.2.dist-info/LICENSE
aiida_sssp-0.1.2.dist-info/METADATA
aiida_sssp-0.1.2.dist-info/WHEEL
aiida_sssp-0.1.2.dist-info/entry_points.txt
aiida_sssp-0.1.2.dist-info/top_level.txt
aiida_sssp-0.1.2.dist-info/RECORD
