Metadata-Version: 2.1
Name: aiida-sssp
Version: 0.1.2
Summary: AiiDA plugin for the Standard Solid State Pseudopotential (SSSP) library
Home-page: https://github.com/aiidateam/aiida-sssp
Author: The AiiDA team
Author-email: developers@aiida.net
License: MIT License
Platform: UNKNOWN
Classifier: Development Status :: 4 - Beta
Classifier: Framework :: AiiDA
Classifier: License :: OSI Approved :: MIT License
Classifier: Operating System :: POSIX :: Linux
Classifier: Operating System :: MacOS :: MacOS X
Classifier: Programming Language :: Python
Classifier: Programming Language :: Python :: 3.5
Classifier: Programming Language :: Python :: 3.6
Classifier: Programming Language :: Python :: 3.7
Classifier: Programming Language :: Python :: 3.8
Requires-Python: >=3.5
Requires-Dist: aiida-core (~=1.2)
Requires-Dist: click (~=7.0)
Requires-Dist: click-completion (~=0.5)
Requires-Dist: requests (~=2.20)
Provides-Extra: pre-commit
Requires-Dist: pre-commit (~=2.2) ; extra == 'pre-commit'
Requires-Dist: prospector (~=1.2) ; extra == 'pre-commit'
Requires-Dist: yapf (~=0.29) ; extra == 'pre-commit'
Provides-Extra: tests
Requires-Dist: pgtest (~=1.3) ; extra == 'tests'
Requires-Dist: pytest (~=5.4) ; extra == 'tests'
